README.md
setup.py
gh_star_timeline/__init__.py
gh_star_timeline/api.py
gh_star_timeline/display.py
gh_star_timeline/events.py
gh_star_timeline/log_tqdm.py
gh_star_timeline/main.py
gh_star_timeline/page_fetcher.py
gh_star_timeline/parse_api.py
gh_star_timeline/timeseries.py
gh_star_timeline/timestamps.py
gh_star_timeline.egg-info/PKG-INFO
gh_star_timeline.egg-info/SOURCES.txt
gh_star_timeline.egg-info/dependency_links.txt
gh_star_timeline.egg-info/entry_points.txt
gh_star_timeline.egg-info/top_level.txt