Metadata-Version: 2.1
Name: gh-star-timeline
Version: 2.0.1
Summary: Command-line tool to keep track of historic stars on github. Machine-useable output.
Home-page: 
Author: @readwithai
Author-email: talwrii@gmail.co
License: GPLv3
